import_guard/__init__.py
import_guard/_guard.py
import_guard/matchers.py
import_guard/models.py
import_guard/observers.py
import_guard/trie.py
import_guard-0.1.2.dist-info/LICENSE
import_guard-0.1.2.dist-info/WHEEL
import_guard-0.1.2.dist-info/METADATA
import_guard-0.1.2.dist-info/RECORD
