Metadata-Version: 2.1
Name: import-guard
Version: 0.1.2
Summary: Enforce that some modules can't be imported from other modules.
Home-page: https://github.com/Anexen/import-guard
Keywords: import,deny,guard,impguard
Author: Anexen
Requires-Python: >=2.7, !=3.0.*, !=3.1.*, !=3.2.*, <4
Classifier: Intended Audience :: Developers
Classifier: Operating System :: OS Independent
Classifier: License :: OSI Approved :: MIT License
Classifier: Programming Language :: Python
Classifier: Programming Language :: Python :: 3
Classifier: Programming Language :: Python :: 3.4
Classifier: Programming Language :: Python :: 3.5
Classifier: Programming Language :: Python :: 3.6
Classifier: Programming Language :: Python :: 3.7
Classifier: Programming Language :: Python :: 3.8
Classifier: Programming Language :: Python :: 3.9
Classifier: Programming Language :: Python :: Implementation :: CPython
Classifier: Programming Language :: Python :: Implementation :: PyPy
